cloudeye/__init__.py
cloudeye/gesture/__init__.py
cloudeye/gesture/model/eval_details.json
cloudeye/gesture/model/model.pdopt
cloudeye/gesture/model/model.pdparams
cloudeye/gesture/model/model.yml
cloudeye-0.0.3.dist-info/METADATA
cloudeye-0.0.3.dist-info/WHEEL
cloudeye-0.0.3.dist-info/top_level.txt
cloudeye-0.0.3.dist-info/RECORD
